cubicweb_postgis/__init__.py
cubicweb_postgis/__pkginfo__.py
cubicweb_postgis/site_cubicweb.py
cubicweb_postgis/views.py
cubicweb_postgis/i18n/en.po
cubicweb_postgis/i18n/es.po
cubicweb_postgis/i18n/fr.po
cubicweb_postgis/migration/precreate.py
cubicweb_postgis/schema/__init__.py
cubicweb_postgis/schema/_ext.postgres.sql
cubicweb_postgis-1.0.0.dist-info/METADATA
cubicweb_postgis-1.0.0.dist-info/WHEEL
cubicweb_postgis-1.0.0.dist-info/entry_points.txt
cubicweb_postgis-1.0.0.dist-info/top_level.txt
cubicweb_postgis-1.0.0.dist-info/RECORD
