Metadata-Version: 2.1
Name: cubicweb-postgis
Version: 1.0.0
Summary: Test for postgis
Home-page: https://forge.extranet.logilab.fr/cubicweb/cubes/cubicweb-postgis
Author: LOGILAB S.A. (Paris, FRANCE)
Author-email: contact@logilab.fr
License: LGPL
Classifier: Environment :: Web Environment
Classifier: Framework :: CubicWeb
Classifier: Programming Language :: Python
Classifier: Programming Language :: Python :: 2
Classifier: Programming Language :: Python :: 3
Classifier: Programming Language :: JavaScript
Classifier: Topic :: Scientific/Engineering :: GIS
Classifier: Topic :: Database
Requires-Python: >=2.7
Requires-Dist: cubicweb (<5.0.0,>=4.0.0)
Requires-Dist: cubicweb-web (<2.0.0,>=1.0.0)
